ptmath/__init__.py
ptmath/precise.py
ptmath-0.1.0.dist-info/METADATA
ptmath-0.1.0.dist-info/WHEEL
ptmath-0.1.0.dist-info/top_level.txt
ptmath-0.1.0.dist-info/RECORD
