Metadata-Version: 2.1
Name: ptmath
Version: 0.1.0
Summary: Math and other funcs
Home-page: https://github.com/funkaclau
Author: funkaclau
